HS23005UNO/_init_.py
HS23005UNO/biseccion.py
HS23005UNO/cramer.py
HS23005UNO/gauss.py
HS23005UNO/gauss_jordan.py
HS23005UNO/gauss_seidel.py
HS23005UNO/jacobi.py
HS23005UNO/lu.py
hs23005uno-0.0.2.dist-info/licenses/LICENSE
hs23005uno-0.0.2.dist-info/METADATA
hs23005uno-0.0.2.dist-info/WHEEL
hs23005uno-0.0.2.dist-info/entry_points.txt
hs23005uno-0.0.2.dist-info/top_level.txt
hs23005uno-0.0.2.dist-info/RECORD
