Metadata-Version: 2.4
Name: HS23005UNO
Version: 0.0.2
Summary: Libreria para resolver sistema de ecuaciones lineales y no lineales.
Author: Noel Alejandro Hernandez Salinas
Author-email: Noel Alejandro Hernandez Salinas <hs23005@ues.edu.sv>
License: MIT
Classifier: Programming Language :: Python :: 3
Classifier: License :: OSI Approved :: MIT License
Requires-Python: >=3.6
License-File: LICENSE
Requires-Dist: numpy
Dynamic: author
Dynamic: license-file
Dynamic: requires-python
